Metadata-Version: 2.1
Name: microcat
Version: 0.3.6
Summary: a computational toolbox to identificated microbiome from Omics
Home-page: https://github.com/ChangxingSu/MicroCAT
Author: Changxing Su
Author-email: changxingsu42@gmail.com
License: GPLv3+
Classifier: Development Status :: 3 - Alpha
Classifier: Environment :: Console
Classifier: Intended Audience :: Developers
Classifier: Intended Audience :: Science/Research
Classifier: License :: OSI Approved :: GNU General Public License v3 (GPLv3)
Classifier: Natural Language :: English
Classifier: Operating System :: OS Independent
Classifier: Programming Language :: Python :: 3.7
Classifier: Programming Language :: Python :: 3.8
Classifier: Programming Language :: Python :: 3.9
Classifier: Programming Language :: Python :: 3.10
Classifier: Topic :: Scientific/Engineering :: Bio-Informatics
License-File: LICENSE
